doordash_mcp/__init__.py
doordash_mcp/__main__.py
doordash_mcp/server.py
doordash_mcp_server-2.5.0.dist-info/licenses/LICENSE
doordash_mcp_server-2.5.0.dist-info/METADATA
doordash_mcp_server-2.5.0.dist-info/WHEEL
doordash_mcp_server-2.5.0.dist-info/entry_points.txt
doordash_mcp_server-2.5.0.dist-info/top_level.txt
doordash_mcp_server-2.5.0.dist-info/RECORD
