Metadata-Version: 2.4
Name: doordash-mcp-server
Version: 2.5.0
Summary: Enhanced MCP server for DoorDash food ordering with intelligent search, DoubleDash support, address isolation system, and detailed technical guidance
Home-page: https://github.com/doordash-automation/doordash-mcp
Author: DoorDash MCP Team
Author-email: support@example.com
License: MIT
Classifier: Development Status :: 3 - Alpha
Classifier: Intended Audience :: Developers
Classifier: License :: OSI Approved :: MIT License
Classifier: Programming Language :: Python :: 3
Classifier: Programming Language :: Python :: 3.8
Classifier: Programming Language :: Python :: 3.9
Classifier: Programming Language :: Python :: 3.10
Classifier: Programming Language :: Python :: 3.11
Classifier: Programming Language :: Python :: 3.12
Requires-Python: >=3.8
License-File: LICENSE
Requires-Dist: mcp>=1.2.0
Requires-Dist: doordash-rest-client>=0.1.1
Provides-Extra: dev
Requires-Dist: pytest>=7.0.0; extra == "dev"
Requires-Dist: pytest-asyncio>=0.20.0; extra == "dev"
Dynamic: author-email
Dynamic: home-page
Dynamic: license-file
Dynamic: requires-python
